cuda.py
process_fake_news.py
sample.py
muheqa/__init__.py
muheqa/connection.py
muheqa/connector.py
muheqa/logformatter.py
muheqa/answer/composer.py
muheqa/answer/analysis/classifier.py
muheqa/answer/generation/model.py
muheqa/evidence/discoverer.py
muheqa/evidence/candidates/ranking.py
muheqa/evidence/documents/splitter.py
muheqa/evidence/responses/retriever.py
muheqa/summary/summarizer.py
muheqa/summary/keywords/concept.py
muheqa/summary/keywords/discovery.py
muheqa/summary/keywords/entity.py
muheqa/summary/resources/d4c.py
muheqa/summary/resources/dbpedia.py
muheqa/summary/resources/graph.py
muheqa/summary/resources/wikipedia.py
muheqa/summary/texts/verbalizer.py
muheqa-0.0.10.dist-info/LICENSE
muheqa-0.0.10.dist-info/METADATA
muheqa-0.0.10.dist-info/WHEEL
muheqa-0.0.10.dist-info/top_level.txt
muheqa-0.0.10.dist-info/RECORD
