Metadata-Version: 2.1
Name: muheqa
Version: 0.0.10
Summary: Multiple and Heterogeneous Question-Answering
Author-email: Carlos Badenes-Olmedo <carlos.badenes@upm.es>
Project-URL: Homepage, https://github.com/librairy/muheqa-core
Project-URL: Bug Tracker, https://github.com/librairy/muheqa-core/issues
Classifier: Programming Language :: Python :: 3
Classifier: License :: OSI Approved :: Apache Software License
Classifier: Operating System :: OS Independent
Classifier: Topic :: Internet :: WWW/HTTP :: Indexing/Search
Classifier: Natural Language :: English
Classifier: Topic :: Software Development :: Libraries
Requires-Python: >=3.7
License-File: LICENSE
Requires-Dist: sparqlwrapper
Requires-Dist: flair
Requires-Dist: unidecode
Requires-Dist: sentence-transformers
